ifk_smhi-0.3.0.dist-info/licenses/LICENSE
smhi/constants.py
smhi/mesan.py
smhi/metfcts.py
smhi/metobs.py
smhi/smhi.py
smhi/strang.py
smhi/utils.py
smhi/models/mesan_model.py
smhi/models/metfcts_model.py
smhi/models/metobs_model.py
smhi/models/strang_model.py
smhi/models/variable_model.py
ifk_smhi-0.3.0.dist-info/METADATA
ifk_smhi-0.3.0.dist-info/WHEEL
ifk_smhi-0.3.0.dist-info/top_level.txt
ifk_smhi-0.3.0.dist-info/RECORD
