Metadata-Version: 2.4
Name: ifk-smhi
Version: 0.3.0
Summary: Inspect and get SMHI data.
Author-email: Anders Nord <dr.anders.nord@gmail.com>, Mladen Gibanica <11275336+mgcth@users.noreply.github.com>
License: MIT
Project-URL: homepage, https://ingenjorsarbeteforklimatet.se/ifk-smhi/
Project-URL: documentation, https://ingenjorsarbeteforklimatet.se/ifk-smhi/
Project-URL: repository, https://github.com/Ingenjorsarbete-For-Klimatet/ifk-smhi
Requires-Python: >=3.9
License-File: LICENSE
Requires-Dist: requests~=2.28
Requires-Dist: pandas~=2.2
Requires-Dist: geopy~=2.2
Requires-Dist: arrow~=1.2
Requires-Dist: shapely~=2.0
Requires-Dist: pydantic~=2.6
Requires-Dist: pandera[mypy]~=0.18
Provides-Extra: lint
Requires-Dist: ruff~=0.3; extra == "lint"
Provides-Extra: type
Requires-Dist: mypy~=1.7; extra == "type"
Requires-Dist: types-requests~=2.31; extra == "type"
Requires-Dist: pandas-stubs~=1.5; extra == "type"
Provides-Extra: test
Requires-Dist: pytest~=7.1; extra == "test"
Requires-Dist: coverage~=6.5; extra == "test"
Requires-Dist: pytest-cov~=4.0; extra == "test"
Provides-Extra: doc
Requires-Dist: mkdocs~=1.4; extra == "doc"
Requires-Dist: mkdocs-material~=8.5; extra == "doc"
Requires-Dist: mkdocstrings[python]~=0.19; extra == "doc"
Provides-Extra: dev
Requires-Dist: ifk-smhi[lint]; extra == "dev"
Requires-Dist: ifk-smhi[type]; extra == "dev"
Requires-Dist: ifk-smhi[test]; extra == "dev"
Requires-Dist: ifk-smhi[doc]; extra == "dev"
Requires-Dist: pre-commit~=2.20; extra == "dev"
Dynamic: license-file
